{
  "$schema": "https://mintlify.com/docs.json",
  "name": "ARM Demos",
  "theme": "aspen",
  "colors": {
    "primary": "#2563EB",
    "light": "#DBEAFE",
    "dark": "#1E3A5F"
  },
  "navbar": {
    "primary": {
      "type": "github",
      "href": "https://github.com/MRRP-lab/arm-demos"
    }
  },
  "footer": {
    "socials": {
      "github": "https://github.com/MRRP-lab/arm-demos"
    }
  },
  "navigation": {
    "tabs": [
      {
        "tab": "Documentation",
        "groups": [
          {
            "group": "Get Started",
            "pages": [
              "introduction",
              "quickstart"
            ]
          },
          {
            "group": "Setup",
            "pages": [
              "setup/environment",
              "setup/hardware",
              "setup/simulation"
            ]
          },
          {
            "group": "Demos",
            "pages": [
              "demos/hand-tracking",
              "demos/pick-and-place",
              "demos/eye-in-hand-calibration"
            ]
          },
          {
            "group": "Packages",
            "pages": [
              "packages/colman-bringup",
              "packages/colman-description",
              "packages/colman-motion",
              "packages/colman-perception",
              "packages/colman-moveit-config"
            ]
          },
          {
            "group": "Reference",
            "pages": [
              "reference/launch-tasks",
              "reference/ros-topics",
              "reference/troubleshooting"
            ]
          }
        ]
      }
    ]
  }
}
